photogrammetry_target_locator/__init__.py
photogrammetry_target_locator/cli.py
photogrammetry_target_locator/config.py
photogrammetry_target_locator/main.py
photogrammetry_target_locator/photogrammetry.py
photogrammetry_target_locator-0.1.2.dist-info/licenses/LICENSE
photogrammetry_target_locator-0.1.2.dist-info/METADATA
photogrammetry_target_locator-0.1.2.dist-info/WHEEL
photogrammetry_target_locator-0.1.2.dist-info/entry_points.txt
photogrammetry_target_locator-0.1.2.dist-info/top_level.txt
photogrammetry_target_locator-0.1.2.dist-info/RECORD
